{
    "Ar36": {
        "error": 0.001690907046563822,
        "error_type": "SEM",
        "filter_outliers_dict": {
            "filter_outliers": true,
            "iterations": 1,
            "std_devs": 3,
            "use_iqr_filtering": false,
            "use_standard_deviation_filtering": false
        },
        "fit": "linear",
        "fn": 119,
        "include_baseline_error": true,
        "n": 120,
        "outlier_excluded": [
            36
        ],
        "reviewed": true,
        "user_excluded": [],
        "value": 0.3987926719973661
    },
    "Ar37": {
        "error": 0.006667364646421763,
        "error_type": "SEM",
        "filter_outliers_dict": {
            "filter_outliers": true,
            "iterations": 1,
            "std_devs": 3,
            "use_iqr_filtering": false,
            "use_standard_deviation_filtering": false
        },
        "fit": "linear",
        "fn": 119,
        "include_baseline_error": true,
        "n": 120,
        "outlier_excluded": [
            0
        ],
        "reviewed": true,
        "user_excluded": [],
        "value": 1.1865741266849166
    },
    "Ar38": {
        "error": 0.006229067856441385,
        "error_type": "SEM",
        "filter_outliers_dict": {
            "filter_outliers": true,
            "iterations": 1,
            "std_devs": 3,
            "use_iqr_filtering": false,
            "use_standard_deviation_filtering": false
        },
        "fit": "linear",
        "fn": 118,
        "include_baseline_error": true,
        "n": 120,
        "outlier_excluded": [
            0,
            1
        ],
        "reviewed": true,
        "user_excluded": [],
        "value": 2.5286213649305944
    },
    "Ar39": {
        "error": 0.02967911980799658,
        "error_type": "SEM",
        "filter_outliers_dict": {
            "filter_outliers": true,
            "iterations": 1,
            "std_devs": 3,
            "use_iqr_filtering": false,
            "use_standard_deviation_filtering": false
        },
        "fit": "linear",
        "fn": 120,
        "include_baseline_error": true,
        "n": 120,
        "outlier_excluded": [],
        "reviewed": true,
        "user_excluded": [],
        "value": 200.55364522740405
    },
    "Ar40": {
        "error": 0.028582753601597847,
        "error_type": "SEM",
        "filter_outliers_dict": {
            "filter_outliers": true,
            "iterations": 1,
            "std_devs": 3,
            "use_iqr_filtering": false,
            "use_standard_deviation_filtering": false
        },
        "fit": "linear",
        "fn": 120,
        "include_baseline_error": true,
        "n": 120,
        "outlier_excluded": [],
        "reviewed": true,
        "user_excluded": [],
        "value": 287.8784376417234
    },
    "Ar41": {
        "error": 0.003989357984395137,
        "error_type": "SEM",
        "filter_outliers_dict": {
            "filter_outliers": true,
            "iterations": 1,
            "std_devs": 2
        },
        "fit": "Average",
        "value": 0.07881796397179748
    }
}