{
    "AX": {
        "error": 0.010884739023244556,
        "error_type": "SEM",
        "filter_outliers_dict": {
            "filter_outliers": true,
            "iterations": 1,
            "std_devs": 3,
            "use_iqr_filtering": false,
            "use_standard_deviation_filtering": false
        },
        "fit": "average",
        "fn": 30,
        "include_baseline_error": false,
        "n": 30,
        "outlier_excluded": [],
        "reviewed": true,
        "user_excluded": [],
        "value": 0.0994486247150538
    },
    "CDD": {
        "error": 1.4048231681606474e-05,
        "error_type": "SEM",
        "filter_outliers_dict": {
            "filter_outliers": true,
            "iterations": 1,
            "std_devs": 10,
            "use_iqr_filtering": false,
            "use_standard_deviation_filtering": false
        },
        "fit": "average",
        "fn": 30,
        "include_baseline_error": false,
        "n": 30,
        "outlier_excluded": [],
        "reviewed": true,
        "user_excluded": [],
        "value": 3.5622349726812294e-05
    },
    "H1": {
        "error": 0.006484428791665584,
        "error_type": "SEM",
        "filter_outliers_dict": {
            "filter_outliers": true,
            "iterations": 1,
            "std_devs": 3,
            "use_iqr_filtering": false,
            "use_standard_deviation_filtering": false
        },
        "fit": "average",
        "fn": 30,
        "include_baseline_error": false,
        "n": 30,
        "outlier_excluded": [],
        "reviewed": true,
        "user_excluded": [],
        "value": 0.04960380782334444
    },
    "H2": {
        "error": 0.006242728746263546,
        "error_type": "SEM",
        "filter_outliers_dict": {
            "filter_outliers": true,
            "iterations": 1,
            "std_devs": 3,
            "use_iqr_filtering": false,
            "use_standard_deviation_filtering": false
        },
        "fit": "average",
        "fn": 30,
        "include_baseline_error": false,
        "n": 30,
        "outlier_excluded": [],
        "reviewed": true,
        "user_excluded": [],
        "value": 0.03956988696785023
    },
    "L1": {
        "error": 0.00561091116054474,
        "error_type": "SEM",
        "filter_outliers_dict": {
            "filter_outliers": true,
            "iterations": 1,
            "std_devs": 3,
            "use_iqr_filtering": false,
            "use_standard_deviation_filtering": false
        },
        "fit": "average",
        "fn": 30,
        "include_baseline_error": false,
        "n": 30,
        "outlier_excluded": [],
        "reviewed": true,
        "user_excluded": [],
        "value": 0.033232219794687504
    },
    "L2": {
        "error": 0.005710320438162181,
        "error_type": "SEM",
        "filter_outliers_dict": {
            "filter_outliers": true,
            "iterations": 1,
            "std_devs": 2
        },
        "fit": "average",
        "value": 0.005086323029487036
    }
}